aviationFormula/__init__.py
aviationFormula/aviationFormula.py
aviationFormula-0.0.2.dist-info/LICENSE
aviationFormula-0.0.2.dist-info/METADATA
aviationFormula-0.0.2.dist-info/WHEEL
aviationFormula-0.0.2.dist-info/top_level.txt
aviationFormula-0.0.2.dist-info/RECORD
