Metadata-Version: 2.1
Name: aviationFormula
Version: 0.0.2
Summary: A collection of formula around aviation and the globe in python.
Home-page: https://github.com/Sowintuu/aviationFormula
Author: Oliver Clemens
Author-email: sowintuu@aol.com
License: UNKNOWN
Platform: UNKNOWN
Classifier: Development Status :: 3 - Alpha
Classifier: Environment :: Console
Classifier: Programming Language :: Python
Classifier: License :: OSI Approved :: GNU General Public License v3 (GPLv3)
Classifier: Operating System :: OS Independent
